maeson/__init__.py
maeson/common.py
maeson/folmap.py
maeson/gistory.py
maeson/maeson.py
maeson-0.0.6.dist-info/licenses/LICENSE
maeson-0.0.6.dist-info/METADATA
maeson-0.0.6.dist-info/WHEEL
maeson-0.0.6.dist-info/entry_points.txt
maeson-0.0.6.dist-info/top_level.txt
maeson-0.0.6.dist-info/RECORD
